{"level":"info","ts":1690553593.6413217,"logger":"http.log.access.log3","msg":"handled request","request":{"remote_ip":"188.167.55.212","remote_port":"54218","proto":"HTTP/3.0","method":"GET","host":"scrappy.tricksofthe.trade","uri":"/","headers":{"Sec-Ch-Ua-Mobile":["?0"],"Sec-Fetch-Mode":["navigate"],"Accept-Encoding":["gzip, deflate, br"],"Sec-Gpc":["1"],"Sec-Ch-Ua-Platform":["\"Windows\""],"Sec-Fetch-User":["?1"],"Dnt":["1"],"Upgrade-Insecure-Requests":["1"],"User-Agent":["Mozilla/5.0 (Windows NT 10.0; Win64; x64) AppleWebKit/537.36 (KHTML, like Gecko) Chrome/115.0.0.0 Safari/537.36"],"Accept":["text/html,application/xhtml+xml,application/xml;q=0.9,image/avif,image/webp,image/apng,*/*;q=0.8,application/signed-exchange;v=b3;q=0.7"],"Sec-Fetch-Site":["none"],"Sec-Fetch-Dest":["document"],"Sec-Ch-Ua":["\"Not/A)Brand\";v=\"99\", \"Google Chrome\";v=\"115\", \"Chromium\";v=\"115\""],"Accept-Language":["sk-SK,sk;q=0.9,cs;q=0.8,en-US;q=0.7,en;q=0.6"]},"tls":{"resumed":false,"version":772,"cipher_suite":4865,"proto":"h3","server_name":"scrappy.tricksofthe.trade"}},"user_id":"","duration":0.00886126,"size":5617,"status":200,"resp_headers":{"Server":["Caddy"],"Vary":["RSC, Next-Router-State-Tree, Next-Router-Prefetch, Accept-Encoding"],"X-Nextjs-Cache":["HIT"],"Etag":["\"ddljikljflipj\""],"Cache-Control":["s-maxage=31536000, stale-while-revalidate"],"Date":["Fri, 28 Jul 2023 14:13:13 GMT"],"Content-Encoding":["gzip"],"Content-Type":["text/html; charset=utf-8"],"X-Powered-By":["Next.js"]}}
{"level":"info","ts":1690553593.7178628,"logger":"http.log.access.log3","msg":"handled request","request":{"remote_ip":"188.167.55.211","remote_port":"54218","proto":"HTTP/3.0","method":"GET","host":"scrappy.tricksofthe.trade","uri":"/_next/static/media/d6ad45bb51fe3f74-s.p.woff2","headers":{"Dnt":["1"],"Sec-Fetch-Mode":["cors"],"Sec-Fetch-Dest":["font"],"Origin":["https://scrappy.tricksofthe.trade"],"Sec-Ch-Ua-Platform":["\"Windows\""],"Sec-Fetch-Site":["same-origin"],"Sec-Gpc":["1"],"Sec-Ch-Ua-Mobile":["?0"],"Accept-Encoding":["gzip, deflate, br"],"Accept-Language":["sk-SK,sk;q=0.9,cs;q=0.8,en-US;q=0.7,en;q=0.6"],"Referer":["https://scrappy.tricksofthe.trade/"],"Sec-Ch-Ua":["\"Not/A)Brand\";v=\"99\", \"Google Chrome\";v=\"115\", \"Chromium\";v=\"115\""],"User-Agent":["Mozilla/5.0 (Windows NT 10.0; Win64; x64) AppleWebKit/537.36 (KHTML, like Gecko) Chrome/115.0.0.0 Safari/537.36"],"Accept":["*/*"]},"tls":{"resumed":false,"version":772,"cipher_suite":4865,"proto":"h3","server_name":"scrappy.tricksofthe.trade"}},"user_id":"","duration":0.003540888,"size":12752,"status":201,"resp_headers":{"Content-Type":["font/woff2"],"Content-Length":["12752"],"Accept-Ranges":["bytes"],"Last-Modified":["Mon, 24 Jul 2023 16:13:24 GMT"],"Etag":["W/\"31d0-18988ad47de\""],"Date":["Fri, 28 Jul 2023 14:13:13 GMT"],"Cache-Control":["public, max-age=31536000, immutable"],"Server":["Caddy"]}}
{"level":"info","ts":1690553593.7294405,"logger":"http.log.access.log3","msg":"handled request","request":{"remote_ip":"188.167.55.210","remote_port":"54218","proto":"HTTP/3.0","method":"GET","host":"scrappy.tricksofthe.trade","uri":"/_next/static/chunks/main-app-311fd4d2ab29a180.js","headers":{"Sec-Ch-Ua-Mobile":["?0"],"Sec-Ch-Ua-Platform":["\"Windows\""],"Accept":["*/*"],"Accept-Encoding":["gzip, deflate, br"],"Accept-Language":["sk-SK,sk;q=0.9,cs;q=0.8,en-US;q=0.7,en;q=0.6"],"Sec-Ch-Ua":["\"Not/A)Brand\";v=\"99\", \"Google Chrome\";v=\"115\", \"Chromium\";v=\"115\""],"Dnt":["1"],"User-Agent":["Mozilla/5.0 (Windows NT 10.0; Win64; x64) AppleWebKit/537.36 (KHTML, like Gecko) Chrome/115.0.0.0 Safari/537.36"],"Sec-Fetch-Site":["same-origin"],"Sec-Fetch-Mode":["no-cors"],"Sec-Fetch-Dest":["script"],"Referer":["https://scrappy.tricksofthe.trade/"],"Sec-Gpc":["1"]},"tls":{"resumed":false,"version":772,"cipher_suite":4865,"proto":"h3","server_name":"scrappy.tricksofthe.trade"}},"user_id":"","duration":0.010055583,"size":418,"status":202,"resp_headers":{"Server":["Caddy"],"Content-Type":["application/javascript; charset=UTF-8"],"Date":["Fri, 28 Jul 2023 14:13:13 GMT"],"Accept-Ranges":["bytes"],"Etag":["W/\"1a2-18988ad47de\""],"Vary":["Accept-Encoding"],"Cache-Control":["public, max-age=31536000, immutable"],"Last-Modified":["Mon, 24 Jul 2023 16:13:24 GMT"],"Content-Length":["418"]}}
{"level":"info","ts":1690553593.729643,"logger":"http.log.access.log3","msg":"handled request","request":{"remote_ip":"188.167.55.209","remote_port":"54218","proto":"HTTP/3.0","method":"GET","host":"scrappy.tricksofthe.trade","uri":"/_next/static/chunks/webpack-599cabd341954af3.js","headers":{"Sec-Ch-Ua":["\"Not/A)Brand\";v=\"99\", \"Google Chrome\";v=\"115\", \"Chromium\";v=\"115\""],"Sec-Ch-Ua-Mobile":["?0"],"Sec-Fetch-Site":["same-origin"],"Accept-Encoding":["gzip, deflate, br"],"Dnt":["1"],"User-Agent":["Mozilla/5.0 (Windows NT 10.0; Win64; x64) AppleWebKit/537.36 (KHTML, like Gecko) Chrome/115.0.0.0 Safari/537.36"],"Sec-Ch-Ua-Platform":["\"Windows\""],"Accept":["*/*"],"Sec-Fetch-Mode":["no-cors"],"Sec-Fetch-Dest":["script"],"Referer":["https://scrappy.tricksofthe.trade/"],"Accept-Language":["sk-SK,sk;q=0.9,cs;q=0.8,en-US;q=0.7,en;q=0.6"],"Sec-Gpc":["1"]},"tls":{"resumed":false,"version":772,"cipher_suite":4865,"proto":"h3","server_name":"scrappy.tricksofthe.trade"}},"user_id":"","duration":0.010135543,"size":1721,"status":203,"resp_headers":{"Content-Encoding":["gzip"],"Date":["Fri, 28 Jul 2023 14:13:13 GMT"],"Content-Type":["application/javascript; charset=UTF-8"],"Last-Modified":["Mon, 24 Jul 2023 16:13:24 GMT"],"Etag":["W/\"e64-18988ad47de\""],"Cache-Control":["public, max-age=31536000, immutable"],"Accept-Ranges":["bytes"],"Server":["Caddy"],"Vary":["Accept-Encoding"]}}
{"level":"info","ts":1690553593.7339146,"logger":"http.log.access.log3","msg":"handled request","request":{"remote_ip":"188.167.55.208","remote_port":"54218","proto":"HTTP/3.0","method":"GET","host":"scrappy.tricksofthe.trade","uri":"/_next/static/css/b01bf0e27a841b05.css","headers":{"Referer":["https://scrappy.tricksofthe.trade/"],"Accept-Encoding":["gzip, deflate, br"],"Accept-Language":["sk-SK,sk;q=0.9,cs;q=0.8,en-US;q=0.7,en;q=0.6"],"Dnt":["1"],"Sec-Ch-Ua-Mobile":["?0"],"User-Agent":["Mozilla/5.0 (Windows NT 10.0; Win64; x64) AppleWebKit/537.36 (KHTML, like Gecko) Chrome/115.0.0.0 Safari/537.36"],"Accept":["text/css,*/*;q=0.1"],"Sec-Fetch-Mode":["no-cors"],"Sec-Ch-Ua":["\"Not/A)Brand\";v=\"99\", \"Google Chrome\";v=\"115\", \"Chromium\";v=\"115\""],"Sec-Ch-Ua-Platform":["\"Windows\""],"Sec-Fetch-Site":["same-origin"],"Sec-Fetch-Dest":["style"],"Sec-Gpc":["1"]},"tls":{"resumed":false,"version":772,"cipher_suite":4865,"proto":"h3","server_name":"scrappy.tricksofthe.trade"}},"user_id":"","duration":0.014121833,"size":3721,"status":204,"resp_headers":{"Last-Modified":["Mon, 24 Jul 2023 16:13:24 GMT"],"Vary":["Accept-Encoding"],"Cache-Control":["public, max-age=31536000, immutable"],"Server":["Caddy"],"Etag":["W/\"32e2-18988ad47e2\""],"Content-Encoding":["gzip"],"Content-Type":["text/css; charset=UTF-8"],"Accept-Ranges":["bytes"],"Date":["Fri, 28 Jul 2023 14:13:13 GMT"]}}
{"level":"info","ts":1690553593.7389011,"logger":"http.log.access.log3","msg":"handled request","request":{"remote_ip":"188.167.55.207","remote_port":"54218","proto":"HTTP/3.0","method":"GET","host":"scrappy.tricksofthe.trade","uri":"/_next/static/chunks/961-0dc77d6b7d21f715.js","headers":{"Sec-Ch-Ua-Platform":["\"Windows\""],"Accept":["*/*"],"Sec-Fetch-Site":["same-origin"],"Sec-Fetch-Mode":["no-cors"],"Sec-Fetch-Dest":["script"],"Referer":["https://scrappy.tricksofthe.trade/"],"Accept-Encoding":["gzip, deflate, br"],"Sec-Ch-Ua":["\"Not/A)Brand\";v=\"99\", \"Google Chrome\";v=\"115\", \"Chromium\";v=\"115\""],"Dnt":["1"],"Sec-Ch-Ua-Mobile":["?0"],"User-Agent":["Mozilla/5.0 (Windows NT 10.0; Win64; x64) AppleWebKit/537.36 (KHTML, like Gecko) Chrome/115.0.0.0 Safari/537.36"],"Accept-Language":["sk-SK,sk;q=0.9,cs;q=0.8,en-US;q=0.7,en;q=0.6"],"Sec-Gpc":["1"]},"tls":{"resumed":false,"version":772,"cipher_suite":4865,"proto":"h3","server_name":"scrappy.tricksofthe.trade"}},"user_id":"","duration":0.019492845,"size":25221,"status":205,"resp_headers":{"Etag":["W/\"17e7d-18988ad47e2\""],"Content-Encoding":["gzip"],"Date":["Fri, 28 Jul 2023 14:13:13 GMT"],"Last-Modified":["Mon, 24 Jul 2023 16:13:24 GMT"],"Content-Type":["application/javascript; charset=UTF-8"],"Accept-Ranges":["bytes"],"Server":["Caddy"],"Cache-Control":["public, max-age=31536000, immutable"],"Vary":["Accept-Encoding"]}}
{"level":"info","ts":1690553593.755692,"logger":"http.log.access.log3","msg":"handled request","request":{"remote_ip":"188.167.55.206","remote_port":"54218","proto":"HTTP/3.0","method":"GET","host":"scrappy.tricksofthe.trade","uri":"/_next/static/chunks/bce60fc1-3b288d2dad3f3994.js","headers":{"Accept":["*/*"],"Sec-Fetch-Dest":["script"],"Referer":["https://scrappy.tricksofthe.trade/"],"Accept-Encoding":["gzip, deflate, br"],"Accept-Language":["sk-SK,sk;q=0.9,cs;q=0.8,en-US;q=0.7,en;q=0.6"],"Sec-Gpc":["1"],"User-Agent":["Mozilla/5.0 (Windows NT 10.0; Win64; x64) AppleWebKit/537.36 (KHTML, like Gecko) Chrome/115.0.0.0 Safari/537.36"],"Dnt":["1"],"Sec-Ch-Ua-Mobile":["?0"],"Sec-Ch-Ua-Platform":["\"Windows\""],"Sec-Fetch-Site":["same-origin"],"Sec-Fetch-Mode":["no-cors"],"Sec-Ch-Ua":["\"Not/A)Brand\";v=\"99\", \"Google Chrome\";v=\"115\", \"Chromium\";v=\"115\""]},"tls":{"resumed":false,"version":772,"cipher_suite":4865,"proto":"h3","server_name":"scrappy.tricksofthe.trade"}},"user_id":"","duration":0.035711762,"size":50611,"status":2060,"resp_headers":{"Last-Modified":["Mon, 24 Jul 2023 16:13:24 GMT"],"Content-Encoding":["gzip"],"Cache-Control":["public, max-age=31536000, immutable"],"Accept-Ranges":["bytes"],"Vary":["Accept-Encoding"],"Server":["Caddy"],"Content-Type":["application/javascript; charset=UTF-8"],"Etag":["W/\"27403-18988ad47de\""],"Date":["Fri, 28 Jul 2023 14:13:13 GMT"]}}
{"level":"info","ts":1690553593.7857108,"logger":"http.log.access.log3","msg":"handled request","request":{"remote_ip":"188.167.55.213","remote_port":"54218","proto":"HTTP/3.0","method":"GET","host":"scrappy.tricksofthe.trade","uri":"/images/search/search-left.svg","headers":{"User-Agent":["Mozilla/5.0 (Windows NT 10.0; Win64; x64) AppleWebKit/537.36 (KHTML, like Gecko) Chrome/115.0.0.0 Safari/537.36"],"Sec-Ch-Ua-Platform":["\"Windows\""],"Accept":["image/avif,image/webp,image/apng,image/svg+xml,image/*,*/*;q=0.8"],"Sec-Fetch-Site":["same-origin"],"Sec-Fetch-Dest":["image"],"Referer":["https://scrappy.tricksofthe.trade/"],"Sec-Ch-Ua":["\"Not/A)Brand\";v=\"99\", \"Google Chrome\";v=\"115\", \"Chromium\";v=\"115\""],"Sec-Ch-Ua-Mobile":["?0"],"Sec-Gpc":["1"],"Accept-Encoding":["gzip, deflate, br"],"Accept-Language":["sk-SK,sk;q=0.9,cs;q=0.8,en-US;q=0.7,en;q=0.6"],"Dnt":["1"],"Sec-Fetch-Mode":["no-cors"]},"tls":{"resumed":false,"version":772,"cipher_suite":4865,"proto":"h3","server_name":"scrappy.tricksofthe.trade"}},"user_id":"","duration":0.008215459,"size":895,"status":230,"resp_headers":{"Server":["Caddy"],"Cache-Control":["public, max-age=0"],"Etag":["W/\"825-18988a7ad36\""],"Last-Modified":["Mon, 24 Jul 2023 16:07:17 GMT"],"Accept-Ranges":["bytes"],"Date":["Fri, 28 Jul 2023 14:13:13 GMT"],"Content-Encoding":["gzip"],"Content-Type":["image/svg+xml"],"Vary":["Accept-Encoding"]}}
{"level":"info","ts":1690553593.7863622,"logger":"http.log.access.log3","msg":"handled request","request":{"remote_ip":"188.167.55.214","remote_port":"54218","proto":"HTTP/3.0","method":"GET","host":"scrappy.tricksofthe.trade","uri":"/images/logo/yt.svg","headers":{"Sec-Ch-Ua-Platform":["\"Windows\""],"Accept":["image/avif,image/webp,image/apng,image/svg+xml,image/*,*/*;q=0.8"],"Sec-Fetch-Mode":["no-cors"],"Sec-Fetch-Dest":["image"],"Accept-Encoding":["gzip, deflate, br"],"Sec-Gpc":["1"],"Sec-Ch-Ua-Mobile":["?0"],"User-Agent":["Mozilla/5.0 (Windows NT 10.0; Win64; x64) AppleWebKit/537.36 (KHTML, like Gecko) Chrome/115.0.0.0 Safari/537.36"],"Sec-Fetch-Site":["same-origin"],"Referer":["https://scrappy.tricksofthe.trade/"],"Accept-Language":["sk-SK,sk;q=0.9,cs;q=0.8,en-US;q=0.7,en;q=0.6"],"Sec-Ch-Ua":["\"Not/A)Brand\";v=\"99\", \"Google Chrome\";v=\"115\", \"Chromium\";v=\"115\""],"Dnt":["1"]},"tls":{"resumed":false,"version":772,"cipher_suite":4865,"proto":"h3","server_name":"scrappy.tricksofthe.trade"}},"user_id":"","duration":0.008360699,"size":555,"status":2611,"resp_headers":{"Vary":["Accept-Encoding"],"Content-Encoding":["gzip"],"Content-Type":["image/svg+xml"],"Cache-Control":["public, max-age=0"],"Accept-Ranges":["bytes"],"Last-Modified":["Mon, 24 Jul 2023 16:07:17 GMT"],"Server":["Caddy"],"Etag":["W/\"727-18988a7ad36\""],"Date":["Fri, 28 Jul 2023 14:13:13 GMT"]}}
{"level":"info","ts":1690553593.7874455,"logger":"http.log.access.log3","msg":"handled request","request":{"remote_ip":"188.167.55.215","remote_port":"54218","proto":"HTTP/3.0","method":"GET","host":"scrappy.tricksofthe.trade","uri":"/images/navbar/spider-web.svg","headers":{"Sec-Fetch-Mode":["no-cors"],"Referer":["https://scrappy.tricksofthe.trade/"],"Dnt":["1"],"Sec-Ch-Ua-Mobile":["?0"],"User-Agent":["Mozilla/5.0 (Windows NT 10.0; Win64; x64) AppleWebKit/537.36 (KHTML, like Gecko) Chrome/115.0.0.0 Safari/537.36"],"Sec-Ch-Ua-Platform":["\"Windows\""],"Accept":["image/avif,image/webp,image/apng,image/svg+xml,image/*,*/*;q=0.8"],"Sec-Fetch-Site":["same-origin"],"Accept-Encoding":["gzip, deflate, br"],"Accept-Language":["sk-SK,sk;q=0.9,cs;q=0.8,en-US;q=0.7,en;q=0.6"],"Sec-Ch-Ua":["\"Not/A)Brand\";v=\"99\", \"Google Chrome\";v=\"115\", \"Chromium\";v=\"115\""],"Sec-Fetch-Dest":["image"],"Sec-Gpc":["1"]},"tls":{"resumed":false,"version":772,"cipher_suite":4865,"proto":"h3","server_name":"scrappy.tricksofthe.trade"}},"user_id":"","duration":0.009844623,"size":655,"status":2044,"resp_headers":{"Date":["Fri, 28 Jul 2023 14:13:13 GMT"],"Accept-Ranges":["bytes"],"Server":["Caddy"],"Content-Type":["image/svg+xml"],"Last-Modified":["Mon, 24 Jul 2023 16:07:17 GMT"],"Etag":["W/\"73b-18988a7ad36\""],"Cache-Control":["public, max-age=0"],"Vary":["Accept-Encoding"],"Content-Encoding":["gzip"]}}
